[
  {
    "command": "open youtube and search lofi",
    "plan": "open youtube and search lofi",
    "success": true,
    "timestamp": "2026-04-07 17:24:18.525295"
  },
  {
    "command": "open youtube and search lofi",
    "plan": "open youtube and search lofi",
    "success": true,
    "timestamp": "2026-04-07 17:24:26.541795"
  },
  {
    "command": "open youtube and search sad",
    "plan": "open youtube and search sad",
    "success": true,
    "timestamp": "2026-04-07 17:24:48.741628"
  },
  {
    "command": "play lofi",
    "plan": "play lofi",
    "success": true,
    "timestamp": "2026-04-07 17:25:11.384672"
  },
  {
    "command": "open youtube and search sad",
    "plan": "open youtube and search sad",
    "success": true,
    "timestamp": "2026-04-07 17:25:25.660674"
  },
  {
    "command": "open youtube and search lofi",
    "plan": "open youtube and search lofi",
    "success": true,
    "timestamp": "2026-04-07 17:25:31.468251"
  },
  {
    "command": "open youtube and search lofi",
    "plan": "open youtube and search lofi",
    "success": true,
    "timestamp": "2026-04-07 17:25:49.473869"
  },
  {
    "command": "play lofi",
    "plan": "play lofi",
    "success": true,
    "timestamp": "2026-04-07 17:25:56.356236"
  },
  {
    "command": "open youtube and search lofi",
    "plan": "open youtube and search lofi",
    "success": true,
    "timestamp": "2026-04-07 17:26:07.019191"
  },
  {
    "command": "open youtube and search lofi",
    "plan": "open youtube and search lofi",
    "success": true,
    "timestamp": "2026-04-07 17:26:14.628066"
  },
  {
    "command": "open youtube and search lofi",
    "plan": "open youtube and search lofi",
    "success": true,
    "timestamp": "2026-04-07 17:26:34.626569"
  },
  {
    "command": "open youtube and search lofi",
    "plan": "open youtube and search lofi",
    "success": true,
    "timestamp": "2026-04-07 17:26:52.651555"
  },
  {
    "command": "open youtube and search lofi",
    "plan": "open youtube and search lofi",
    "success": true,
    "timestamp": "2026-04-07 17:28:56.302033"
  }
]